icometrix_sdk/__init__.py
icometrix_sdk/_version.py
icometrix_sdk/authentication.py
icometrix_sdk/exceptions.py
icometrix_sdk/logger.py
icometrix_sdk/anonymizer/__init__.py
icometrix_sdk/anonymizer/anonymizer.py
icometrix_sdk/anonymizer/config.py
icometrix_sdk/anonymizer/exceptions.py
icometrix_sdk/anonymizer/hash_factory.py
icometrix_sdk/anonymizer/models.py
icometrix_sdk/anonymizer/policy.py
icometrix_sdk/anonymizer/utils.py
icometrix_sdk/anonymizer/tests/__init__.py
icometrix_sdk/anonymizer/tests/test_anonimizer.py
icometrix_sdk/anonymizer/tests/test_hash.py
icometrix_sdk/anonymizer/tests/test_hash_factory.py
icometrix_sdk/anonymizer/tests/test_policy.py
icometrix_sdk/anonymizer/tests/test_policy_group.py
icometrix_sdk/anonymizer/tests/test_replace.py
icometrix_sdk/anonymizer/tests/test_round.py
icometrix_sdk/anonymizer/tests/test_utils.py
icometrix_sdk/anonymizer/tests/utils.py
icometrix_sdk/anonymizer/tests/datasets/anonymized_md5.dcm
icometrix_sdk/anonymizer/tests/datasets/anonymized_sha3.dcm
icometrix_sdk/anonymizer/tests/datasets/ib_anonymized.dcm
icometrix_sdk/anonymizer/tests/datasets/original.dcm
icometrix_sdk/models/__init__.py
icometrix_sdk/models/base.py
icometrix_sdk/models/customer_report_entity.py
icometrix_sdk/models/customer_result_entity.py
icometrix_sdk/models/job_entity.py
icometrix_sdk/models/patient_entity.py
icometrix_sdk/models/pipeline_result_entity.py
icometrix_sdk/models/project_entity.py
icometrix_sdk/models/series_entity.py
icometrix_sdk/models/study_entity.py
icometrix_sdk/models/upload_entity.py
icometrix_sdk/models/user_entity.py
icometrix_sdk/resources/__init__.py
icometrix_sdk/resources/customer_reports.py
icometrix_sdk/resources/customer_results.py
icometrix_sdk/resources/patients.py
icometrix_sdk/resources/pipeline_results.py
icometrix_sdk/resources/profile.py
icometrix_sdk/resources/projects.py
icometrix_sdk/resources/series.py
icometrix_sdk/resources/studies.py
icometrix_sdk/resources/uploads.py
icometrix_sdk-0.0.9.dist-info/METADATA
icometrix_sdk-0.0.9.dist-info/WHEEL
icometrix_sdk-0.0.9.dist-info/licenses/LICENSE
icometrix_sdk-0.0.9.dist-info/RECORD
