Metadata-Version: 2.4
Name: icometrix-SDK
Version: 0.0.9
Summary: icometrix-SDK is a Software Development Kit (SDK) for Python, which allows Python developers to write software that interacts with the icometrix API.
Project-URL: Homepage, https://github.com/icometrix/icometrix-sdk
Project-URL: Issues, https://github.com/icometrix/icometrix-sdk/issues
Author-email: Jeroen Pinxten <jeroen.pinxten@icometrix.com>
License-File: LICENSE
Classifier: Intended Audience :: Developers
Classifier: License :: OSI Approved :: MIT License
Classifier: Operating System :: OS Independent
Classifier: Programming Language :: Python :: 3
Classifier: Programming Language :: Python :: 3.9
Classifier: Programming Language :: Python :: 3.12
Requires-Python: >=3.9
